[
{
  "text": "Ras is ubiquitinated by Mek.  Following its ubiquitination, Ras is bound to SMURF.",
  "e1-label": "Positive_Regulation",
  "e1-sentence": "Ras is ubiquitinated by Mek.",
  "e1-tokens": ["Ras", "is", "ubiquitinated", "by", "Mek", "."],
  "e1-trigger": "ubiquitinated",
  "e1-trigger-start": 2,
  "e1-trigger-end": 3,
  "e2-sentence": "Following its ubiquitination, Ras is bound to SMURF.",
  "e2-tokens": ["Following", "its", "ubiquitination", ",", "Ras", "is", "bound", "to", "SMURF", "."],
  "e2-trigger": "bound",
  "e2-trigger-start": 6,
  "e2-trigger-end": 7,
  "annotator-id": "",
  "label": "",
  "cross-sentence": true,
  "paper-id": ""
},
{
  "text": "Ras is phosphorylated by Mek.  Following its phosphorylation, Ras is bound to SMURF.",
  "e1-label": "Positive_Regulation",
  "e1-sentence": "Ras is phosphorylated by Mek.",
  "e1-tokens": ["Ras", "is", "phosphorylated", "by", "Mek", "."],
  "e1-trigger": "phosphorylated",
  "e1-trigger-start": 2,
  "e1-trigger-end": 3,
  "e2-sentence": "Following its phosphorylation, Ras is bound to SMURF.",
  "e2-tokens": ["Following", "its", "phosphorylation", ",", "Ras", "is", "bound", "to", "SMURF", "."],
  "e2-trigger": "bound",
  "e2-trigger-start": 6,
  "e2-trigger-end": 7,
  "annotator-id": "",
  "label": "",
  "cross-sentence": true,
  "paper-id": ""
}
]
